ahb_slave.v
module ahb_slave(input hclk,hresetn,hwrite,hreadyin,input [1:0]htrans,input [31:0] haddr,hwdata,prdata,
    output reg valid, hwritereg,output [1:0] hresp,output reg [2:0]tempselx, output reg [31:0] haddr1, haddr2, hwdata1, hwdata2,output [31:0] hrdata);

always@(posedge hclk)
begin
    if(!hresetn)
    begin
        haddr1 <= 0;
        haddr2 <= 0;
    end
    else
    begin
        haddr1 <= haddr;
        haddr2<= haddr1;
    end
end

always@(posedge hclk)
begin
    if(!hresetn)
    begin
        hwdata1 <= 0;
        hwdata2 <= 0;
    end
    else
    begin
        hwdata1 <= hwdata;
        hwdata2 <= hwdata1;
    end
end

always@(*)
begin
    if(haddr >= 32'h8000_0000 && haddr <= 32'h8400_0000)
        tempselx <= 3'b001;
    else if(haddr > 32'h8400_0000 && haddr <= 32'h8800_0000)
        tempselx <= 3'b010;
    else if(haddr > 32'h8800_0000 && haddr <= 32'h8c00_0000)
        tempselx <= 3'b100;
    else
        tempselx <= 3'b000;
end

always@(haddr,htrans)
begin
    if((haddr >= 32'h8000_0000 && haddr <= 32'h8c00_0000) && (htrans == 2'b10 || htrans == 2'b11))
        valid <= 1'b1;
    else
        valid <= 1'b0;
end

always@(posedge hclk)
begin
    if(hwrite && hresetn)
        hwritereg <= 1'b1;
    else
        hwritereg <= 1'b0;
end

assign hrdata = prdata;
assign hresp = 2'b00;

endmodule

ahb_tb.v

`timescale 1ns/100ps

module ahb_slave_tb;
  parameter CYCLE = 10;

  reg hclk, hresetn;
  reg hwrite, hreadyin;
  reg [31:0] hwdata, haddr, prdata;
  reg [1:0] htrans;
  wire [1:0] hresp;
  wire [31:0] hrdata;
  wire valid;
  wire [31:0] haddr1, haddr2, hwdata1, hwdata2;
  wire [2:0] tempselx;
  wire hwritereg;

  // Instantiate the AHB Slave
  ahb_slave DUT (
    .hclk(hclk),
    .hresetn(hresetn),
    .hwrite(hwrite),
    .hreadyin(hreadyin),
    .hwdata(hwdata),
    .haddr(haddr),
    .prdata(prdata),
    .htrans(htrans),
    .hresp(hresp),
    .hrdata(hrdata),
    .valid(valid),
    .haddr1(haddr1),
    .haddr2(haddr2),
    .hwdata1(hwdata1),
    .hwdata2(hwdata2),
    .tempselx(tempselx),
    .hwritereg(hwritereg)
  );

  // Clock generation
  always #(CYCLE/2) hclk = ~hclk;

  initial begin
    $dumpfile("ahb_slave.vcd");
    $dumpvars(0, ahb_slave_tb);

    // Initial reset
    hresetn = 0;
    hclk = 0;
    hwrite = 0;
    hreadyin = 1;
    hwdata = 0;
    haddr = 0;
    htrans = 2'b00;
	prdata = 32'b3000_0000;
    #20;
    hresetn = 1;

    // Test write
    haddr = 32'h8000_0000;
    hwrite = 1;
    htrans = 2'b10;
    hwdata = 32'hDEAD_BEEF;
    #CYCLE;

    // Test read
    hwrite = 0;
    #CYCLE;

    // Test invalid address
    haddr = 32'h9000_0000;
    hwrite = 0;
    htrans = 2'b10;
    #CYCLE;

    $finish;
  end
endmodule

ahb_slave.vcd
$date
	Wed Feb 18 09:36:06 2026
$end
$version
	Icarus Verilog
$end
$timescale
	100ps
$end
$scope module ahb_slave_tb $end
$var wire 2 ! hresp [1:0] $end
$var wire 1 " valid $end
$var wire 3 # tempselx [2:0] $end
$var wire 1 $ hwritereg $end
$var wire 32 % hwdata2 [31:0] $end
$var wire 32 & hwdata1 [31:0] $end
$var wire 32 ' hrdata [31:0] $end
$var wire 32 ( haddr2 [31:0] $end
$var wire 32 ) haddr1 [31:0] $end
$var parameter 32 * CYCLE $end
$var reg 32 + haddr [31:0] $end
$var reg 1 , hclk $end
$var reg 1 - hreadyin $end
$var reg 1 . hresetn $end
$var reg 2 / htrans [1:0] $end
$var reg 32 0 hwdata [31:0] $end
$var reg 1 1 hwrite $end
$var reg 32 2 prdata [31:0] $end
$scope module DUT $end
$var wire 32 3 haddr [31:0] $end
$var wire 1 , hclk $end
$var wire 32 4 hrdata [31:0] $end
$var wire 1 - hreadyin $end
$var wire 1 . hresetn $end
$var wire 2 5 hresp [1:0] $end
$var wire 2 6 htrans [1:0] $end
$var wire 32 7 hwdata [31:0] $end
$var wire 1 1 hwrite $end
$var wire 32 8 prdata [31:0] $end
$var reg 32 9 haddr1 [31:0] $end
$var reg 32 : haddr2 [31:0] $end
$var reg 32 ; hwdata1 [31:0] $end
$var reg 32 < hwdata2 [31:0] $end
$var reg 1 $ hwritereg $end
$var reg 3 = tempselx [2:0] $end
$var reg 1 " valid $end
$upscope $end
$upscope $end
$enddefinitions $end
$comment Show the parameter values. $end
$dumpall
b1010 *
$end
#0
$dumpvars
b0 =
bx <
bx ;
bx :
bx 9
bx 8
b0 7
b0 6
b0 5
bx 4
b0 3
bx 2
01
b0 0
b0 /
0.
1-
0,
b0 +
bx )
bx (
bx '
bx &
bx %
x$
b0 #
0"
b0 !
$end
#50
b0 (
b0 :
b0 )
b0 9
b0 %
b0 <
b0 &
b0 ;
0$
1,
#100
0,
#150
1,
#200
1"
b1 #
b1 =
0,
b11011110101011011011111011101111 0
b11011110101011011011111011101111 7
b10 /
b10 6
11
b10000000000000000000000000000000 +
b10000000000000000000000000000000 3
1.
#250
b10000000000000000000000000000000 )
b10000000000000000000000000000000 9
b11011110101011011011111011101111 &
b11011110101011011011111011101111 ;
1$
1,
#300
0,
01
#350
0$
b11011110101011011011111011101111 %
b11011110101011011011111011101111 <
b10000000000000000000000000000000 (
b10000000000000000000000000000000 :
1,
#400
0"
b0 #
b0 =
0,
b10010000000000000000000000000000 +
b10010000000000000000000000000000 3
#450
b10010000000000000000000000000000 )
b10010000000000000000000000000000 9
1,
